{
  "$schema": "https://www.graphql-code-generator.com/config.schema.json",
  "schema": "./fuel-core-schema.graphql",
  "documents": "./src/operations.graphql",
  "generates": {
    "./src/__generated__/operations.ts": {
      "plugins": [
        { "typescript": {} },
        { "typescript-operations": {} },
        { "typescript-generic-sdk": {} }
      ],
      "config": {
        "scalars": {
          "DateTime": "string",
          "HexString": "string",
          "Bytes32": "string",
          "UtxoId": "string",
          "U64": "string",
          "Address": "string",
          "BlockId": "string",
          "TransactionId": "string",
          "AssetId": "string",
          "ContractId": "string",
          "Salt": "string",
          "Nonce": "string",
          "Tai64Timestamp": "string"
        },
        "useTypeImports": true,
        "nonOptionalTypename": true,
        "typesPrefix": "Gql"
      }
    }
  }
}
